todotxt_machine/__init__.py
todotxt_machine/cli.py
todotxt_machine/colorscheme.py
todotxt_machine/completer.py
todotxt_machine/keys.py
todotxt_machine/screen.py
todotxt_machine/terminal_operations.py
todotxt_machine/todo.py
todotxt_machine/urwid_ui.py
todotxt_machine/colors/base16-dark
todotxt_machine/colors/base16-dark-256
todotxt_machine/colors/base16-light
todotxt_machine/colors/base16-light-256
todotxt_machine/colors/default
todotxt_machine/colors/solarized-dark
todotxt_machine/colors/solarized-light
todotxt_machine/test/__init__.py
todotxt_machine/test/terminal_operations_test.py
todotxt_machine/test/todo_test.py
todotxt_machine-2.2.2.dist-info/DESCRIPTION.rst
todotxt_machine-2.2.2.dist-info/entry_points.txt
todotxt_machine-2.2.2.dist-info/METADATA
todotxt_machine-2.2.2.dist-info/metadata.json
todotxt_machine-2.2.2.dist-info/RECORD
todotxt_machine-2.2.2.dist-info/top_level.txt
todotxt_machine-2.2.2.dist-info/WHEEL
