Metadata-Version: 2.0
Name: todotxt-machine
Version: 2.2.2
Summary: An interactive terminal based todo.txt file editor with an interface similar to mutt
Home-page: https://github.com/AnthonyDiGirolamo/todotxt-machine
Author: Anthony DiGirolamo
Author-email: anthony.digirolamo@gmail.com
License: UNKNOWN
Keywords: todotxt,todo.txt,todo,terminal,urwid,curses,console
Platform: UNKNOWN
Classifier: Development Status :: 4 - Beta
Classifier: Environment :: Console :: Curses
Classifier: Intended Audience :: End Users/Desktop
Classifier: License :: OSI Approved :: GNU General Public License v3 (GPLv3)
Classifier: Natural Language :: English
Classifier: Operating System :: POSIX :: Linux
Classifier: Operating System :: MacOS
Classifier: Programming Language :: Python :: 2.7
Classifier: Programming Language :: Python :: 3.3
Classifier: Topic :: Office/Business :: Scheduling
Requires-Dist: setuptools
Requires-Dist: docopt (>=0.6.2)
Requires-Dist: urwid (>=1.2.1)
